itk/Configuration/NornirConfig.py
itk/Configuration/Nornir_snake_case.py
itk/NornirPython.py
itk/_NornirPython.so
itk/itkIRRefineGridPython.py
itk_nornir-0.3.1.dist-info/METADATA
itk_nornir-0.3.1.dist-info/WHEEL
itk_nornir-0.3.1.dist-info/licenses/LICENSE
itk_nornir-0.3.1.dist-info/RECORD
