Metadata-Version: 2.1
Name: itk-nornir
Version: 0.3.1
Summary: Nornir's takes large sets of overlapping images in 2D and produces registered (a.k.a. aligned) 2D and 3D volumes of any size and scale.
Keywords: itk
Author-Email: Matt McCormick <matt.mccormick@kitware.com>, =?utf-8?b?RMW+ZW5hbiBadWtpxIc=?= <dzenan.zukic@kitware.com>, Josh Cates <josh.cates@kitware.com>
License:                     GNU GENERAL PUBLIC LICENSE
Classifier: Development Status :: 4 - Beta
Classifier: Intended Audience :: Developers
Classifier: Intended Audience :: Education
Classifier: Intended Audience :: Healthcare Industry
Classifier: Intended Audience :: Science/Research
Classifier: Operating System :: Android
Classifier: Operating System :: MacOS
Classifier: Operating System :: Microsoft :: Windows
Classifier: Operating System :: POSIX
Classifier: Operating System :: Unix
Classifier: Programming Language :: C++
Classifier: Programming Language :: Python
Classifier: Topic :: Scientific/Engineering
Classifier: Topic :: Scientific/Engineering :: Information Analysis
Classifier: Topic :: Scientific/Engineering :: Medical Science Apps.
Classifier: Topic :: Software Development :: Libraries
Project-URL: Download, https://github.com/nornir/ITKNornir
Project-URL: Homepage, https://github.com/nornir/ITKNornir
Requires-Python: >=3.8
Requires-Dist: itk==5.4.*
